notebook_logger/__init__.py
notebook_logger/logger.py
notebook_logger-0.1.3.dist-info/LICENSE
notebook_logger-0.1.3.dist-info/METADATA
notebook_logger-0.1.3.dist-info/WHEEL
notebook_logger-0.1.3.dist-info/top_level.txt
notebook_logger-0.1.3.dist-info/RECORD
