Metadata-Version: 2.1
Name: notebook-logger
Version: 0.1.3
Summary: Simple logger for jupyter notebook user
Home-page: https://github.com/asulikeit/notebook-logger
Author: Daniel Lee
Author-email: rootuser.kr@gmail.com
License: Apache-2.0
Classifier: Programming Language :: Python :: 3
Classifier: License :: OSI Approved :: Apache Software License
Classifier: Operating System :: OS Independent
License-File: LICENSE
